e2_tts_mlx/__init__.py
e2_tts_mlx/data.py
e2_tts_mlx/model.py
e2_tts_mlx/trainer.py
mlx_e2_tts-0.0.6.dist-info/LICENSE
mlx_e2_tts-0.0.6.dist-info/METADATA
mlx_e2_tts-0.0.6.dist-info/WHEEL
mlx_e2_tts-0.0.6.dist-info/top_level.txt
mlx_e2_tts-0.0.6.dist-info/RECORD
